neuroquery_image_search/__init__.py
neuroquery_image_search/_datasets.py
neuroquery_image_search/_searching.py
neuroquery_image_search/data/VERSION.txt
neuroquery_image_search/data/__init__.py
neuroquery_image_search/data/search_results_template.html
neuroquery_image_search-0.1.dist-info/LICENSE
neuroquery_image_search-0.1.dist-info/METADATA
neuroquery_image_search-0.1.dist-info/WHEEL
neuroquery_image_search-0.1.dist-info/entry_points.txt
neuroquery_image_search-0.1.dist-info/top_level.txt
neuroquery_image_search-0.1.dist-info/RECORD
